pyslink.py
pyslink-0.4.0.dist-info/LICENSE
pyslink-0.4.0.dist-info/METADATA
pyslink-0.4.0.dist-info/WHEEL
pyslink-0.4.0.dist-info/entry_points.txt
pyslink-0.4.0.dist-info/RECORD
