Metadata-Version: 2.1
Name: pyslink
Version: 0.4.0
Summary: Soft link a file/directory with python site-packages directory
License: BSD-3-Clause
Author: Quantmind
Author-email: message@quantmind.com
Requires-Python: >=3.8,<4.0
Classifier: License :: OSI Approved :: BSD License
Classifier: Programming Language :: Python :: 3
Classifier: Programming Language :: Python :: 3.8
Classifier: Programming Language :: Python :: 3.9
Classifier: Programming Language :: Python :: 3.10
Classifier: Programming Language :: Python :: 3.11
